odoo/addons/easy_my_coop_es/README.rst
odoo/addons/easy_my_coop_es/__init__.py
odoo/addons/easy_my_coop_es/__manifest__.py
odoo/addons/easy_my_coop_es/models/__init__.py
odoo/addons/easy_my_coop_es/models/coop.py
odoo/addons/easy_my_coop_es/readme/DESCRIPTION.rst
odoo/addons/easy_my_coop_es/static/description/index.html
odoo/addons/easy_my_coop_es/views/become_company_cooperator_view.xml
odoo/addons/easy_my_coop_es/views/become_cooperator_view.xml
odoo/addons/easy_my_coop_es/views/subscription_request_view.xml
odoo12_addon_easy_my_coop_es-12.0.0.0.16.dist-info/METADATA
odoo12_addon_easy_my_coop_es-12.0.0.0.16.dist-info/WHEEL
odoo12_addon_easy_my_coop_es-12.0.0.0.16.dist-info/top_level.txt
odoo12_addon_easy_my_coop_es-12.0.0.0.16.dist-info/RECORD
