Metadata-Version: 2.1
Name: odoo12-addon-easy-my-coop-es
Version: 12.0.0.0.16
Summary: Easy My Coop localization for Spain
Home-page: https://coopdevs.org
Author: Coop IT Easy SCRLfs, Coopdevs Treball SCCL
License: AGPL-3
Platform: UNKNOWN
Classifier: Programming Language :: Python
Classifier: Framework :: Odoo
Classifier: License :: OSI Approved :: GNU Affero General Public License v3
Requires-Python: >=3.5
Requires-Dist: odoo12-addon-easy-my-coop
Requires-Dist: odoo (<12.1dev,>=12.0a)
